flake8_less_than/checker.py
flake8_less_than-0.1.0.dist-info/LICENSE
flake8_less_than-0.1.0.dist-info/METADATA
flake8_less_than-0.1.0.dist-info/WHEEL
flake8_less_than-0.1.0.dist-info/entry_points.txt
flake8_less_than-0.1.0.dist-info/RECORD
