Metadata-Version: 2.1
Name: flake8-less-than
Version: 0.1.0
Summary: 
License: ISC
Author: Autumn Russell
Author-email: autumn@adrusi.com
Requires-Python: >=3.11,<4.0
Classifier: License :: OSI Approved
Classifier: License :: OSI Approved :: ISC License (ISCL)
Classifier: Operating System :: OS Independent
Classifier: Programming Language :: Python :: 3
Classifier: Programming Language :: Python :: 3.11
Requires-Dist: flake8
